Metadata-Version: 2.1
Name: pypi-package-guide
Version: 0.0.2
Summary: This is a PYPI package template
Home-page: https://github.com/cr0wg4n/pypi-package-guide
Author: Mauricio Matias
Author-email: xxx@xxx.io
License: MIT
Project-URL: Bug Tracker, https://github.com/cr0wg4n/pypi-package-guide/issues
Keywords: template,pypi-guide,pypi
Platform: UNKNOWN
Classifier: Programming Language :: Python :: 3.6
Classifier: Operating System :: POSIX :: Linux
Classifier: License :: OSI Approved :: MIT License
Classifier: Development Status :: 3 - Alpha
Classifier: Intended Audience :: Developers
Classifier: Topic :: Software Development :: Build Tools
Requires-Python: >=3.6
License-File: LICENSE
